cryptopay/__init__.py
cryptopay/api.py
cryptopay/exceptions.py
tests/__init__.py
tests/test_api.py
tests/test_permissions.py
cryptopay-0.1.2.dist-info/LICENSE
cryptopay-0.1.2.dist-info/METADATA
cryptopay-0.1.2.dist-info/WHEEL
cryptopay-0.1.2.dist-info/top_level.txt
cryptopay-0.1.2.dist-info/RECORD
