Metadata-Version: 2.1
Name: cryptopay
Version: 0.1.2
Summary: Crypto.com pay module
Home-page: https://github.com/Pipoline/cryptopay
Author: Peter Gonda
Author-email: peter@pipoline.com
License: MIT
Platform: UNKNOWN
Classifier: Programming Language :: Python :: 3
Classifier: License :: OSI Approved :: MIT License
Classifier: Natural Language :: English
Classifier: Topic :: Utilities
Classifier: Programming Language :: Python
Classifier: Programming Language :: Python :: 3
Classifier: Operating System :: OS Independent
